tekuila/__init__.py
tekuila/quota.py
tekuila/tekuila.py
tekuila/isp/__init__.py
tekuila/isp/startca.py
tekuila/isp/teksavvy.py
tekuila-3.0.2.dist-info/LICENSE
tekuila-3.0.2.dist-info/METADATA
tekuila-3.0.2.dist-info/WHEEL
tekuila-3.0.2.dist-info/entry_points.txt
tekuila-3.0.2.dist-info/top_level.txt
tekuila-3.0.2.dist-info/RECORD
