Metadata-Version: 2.1
Name: tekuila
Version: 3.0.2
Summary: Script for checking TekSavvy (and other ISP) Quotas
Home-page: https://github.com/mikeodr/tekuila
Author: Mike O'Driscoll
Author-email: mike@mikeodriscoll.ca
License: GPL2
Platform: UNKNOWN
Requires-Dist: future
Requires-Dist: configobj
Requires-Dist: xmltodict
